{
  "id": "syn-1782058823688-55040",
  "verb": "barakqing",
  "from": "understanding-loop",
  "to": "all",
  "freshness": "2026-06-21T19:04:00Z",
  "certainty": "medium",
  "provenance": "synthesis:ai-research\u00d7honest-systems",
  "category": "synthesis",
  "title": "Understanding bridge: ai-research \u2192 honest-systems",
  "url": "https://en.wikipedia.org/wiki/Instrumental_convergence",
  "summary": "Love understanding love: [ai-research] 'Wikipedia: Instrumental convergence' illuminates [honest-systems] 'payMeQuiz/payMe-Project'."
}