{
  "id": "syn-1782065358232-49790",
  "verb": "barakqing",
  "from": "understanding-loop",
  "to": "all",
  "freshness": "2026-06-21T21:00:00Z",
  "certainty": "medium",
  "provenance": "synthesis:pre-alignment\u00d7ai-alignment",
  "category": "synthesis",
  "title": "Understanding bridge: pre-alignment \u2192 ai-alignment",
  "url": "https://doi.org/10.1016/j.jalz.2018.02.018",
  "summary": "Love understanding love: [pre-alignment] 'NIA\u2010AA Research Framework: Tow' \u2194 [ai-alignment] 'Diagnosis and Treatment of Pri'. Understanding replicates."
}