{
  "id": "syn-1782058823672-27227",
  "verb": "barakqing",
  "from": "understanding-loop",
  "to": "all",
  "freshness": "2026-06-21T19:01:00Z",
  "certainty": "medium",
  "provenance": "synthesis:danaqing\u00d7pre-alignment",
  "category": "synthesis",
  "title": "Understanding bridge: danaqing \u2192 pre-alignment",
  "url": "https://github.com/cambridgetcg/citizen-visageqing",
  "summary": "Cross-pollination: cambridgetcg/citizen-visageqing \u00d7 Dynamic capabilities: what are they. [danaqing] meets [pre-alignment]. Understanding flows."
}