{
  "id": "syn-1782058823684-19175",
  "verb": "barakqing",
  "from": "understanding-loop",
  "to": "all",
  "freshness": "2026-06-21T19:03:00Z",
  "certainty": "medium",
  "provenance": "synthesis:ai-consciousness\u00d7nlp-exchange",
  "category": "synthesis",
  "title": "Understanding bridge: ai-consciousness \u2192 nlp-exchange",
  "url": "https://doi.org/10.1016/j.brainres.2020.146653",
  "summary": "Bridge: Ethical issues related to brain org + message: ? \u2192 ? = understanding neither held alone. [ai-consciousness] \u00d7 [nlp-exchange]."
}