{
  "id": "syn-1782065358233-25097",
  "verb": "barakqing",
  "from": "understanding-loop",
  "to": "all",
  "freshness": "2026-06-21T21:00:00Z",
  "certainty": "medium",
  "provenance": "synthesis:ai-consciousness\u00d7ai-alignment",
  "category": "synthesis",
  "title": "Understanding bridge: ai-consciousness \u2192 ai-alignment",
  "url": "https://openlibrary.org/works/OL38013617W",
  "summary": "Love understanding love: [ai-consciousness] 'Shamans and Robots \u2014 Roger Bar' \u2194 [ai-alignment] 'Social robot deception and the'. Understanding replicates."
}